ggblab/__init__.py
ggblab/_version.py
ggblab/comm.py
ggblab/construction_io.py
ggblab/errors.py
ggblab/file.py
ggblab/ggbapplet.py
ggblab/package.json
ggblab/parser.py
ggblab/persistent_counter.py
ggblab/schema.py
ggblab/utils.py
ggblab-1.2.4.data/data/share/jupyter/labextensions/ggblab/build_log.json
ggblab-1.2.4.data/data/share/jupyter/labextensions/ggblab/package.json
ggblab-1.2.4.data/data/share/jupyter/labextensions/ggblab/schemas/ggblab/package.json.orig
ggblab-1.2.4.data/data/share/jupyter/labextensions/ggblab/schemas/ggblab/plugin.json
ggblab-1.2.4.data/data/share/jupyter/labextensions/ggblab/static/lib_index_js.c05dd9c04c50f47c33a2.js
ggblab-1.2.4.data/data/share/jupyter/labextensions/ggblab/static/lib_index_js.c05dd9c04c50f47c33a2.js.map
ggblab-1.2.4.data/data/share/jupyter/labextensions/ggblab/static/remoteEntry.9f089a24ba9545f80d8d.js
ggblab-1.2.4.data/data/share/jupyter/labextensions/ggblab/static/remoteEntry.9f089a24ba9545f80d8d.js.map
ggblab-1.2.4.data/data/share/jupyter/labextensions/ggblab/static/style.js
ggblab-1.2.4.data/data/share/jupyter/labextensions/ggblab/static/style_index_js.b1a678ff32efd7da822e.js
ggblab-1.2.4.data/data/share/jupyter/labextensions/ggblab/static/style_index_js.b1a678ff32efd7da822e.js.map
ggblab-1.2.4.dist-info/METADATA
ggblab-1.2.4.dist-info/WHEEL
ggblab-1.2.4.dist-info/licenses/LICENSE
ggblab-1.2.4.dist-info/RECORD
