Metadata-Version: 2.4
Name: ggblab
Version: 1.2.4
Summary: A JupyterLab extension for learning geometry and Python programming side-by-side with GeoGebra.
Project-URL: Homepage, https://github.com/moyhig-ecs/ggblab#readme
Project-URL: Bug Tracker, https://github.com/moyhig-ecs/ggblab/issues
Project-URL: Repository, https://github.com/moyhig-ecs/ggblab
Author-email: Manabu Higashida <manabu@higashida.net>
License: BSD 3-Clause License
License-File: LICENSE
Keywords: jupyter,jupyterlab,jupyterlab-extension
Classifier: Framework :: Jupyter
Classifier: Framework :: Jupyter :: JupyterLab
Classifier: Framework :: Jupyter :: JupyterLab :: 4
Classifier: Framework :: Jupyter :: JupyterLab :: Extensions
Classifier: Framework :: Jupyter :: JupyterLab :: Extensions :: Prebuilt
Classifier: License :: OSI Approved :: BSD License
Classifier: Programming Language :: Python
Classifier: Programming Language :: Python :: 3
Classifier: Programming Language :: Python :: 3.10
Classifier: Programming Language :: Python :: 3.11
Classifier: Programming Language :: Python :: 3.12
Classifier: Programming Language :: Python :: 3.13
Classifier: Programming Language :: Python :: 3.14
Requires-Python: >=3.10
Requires-Dist: aiofiles
Requires-Dist: ipykernel
Requires-Dist: ipylab
Requires-Dist: networkx
Requires-Dist: polars
Requires-Dist: websockets
Requires-Dist: xmlschema
